.copier-answers.yml
.gitignore
.pre-commit-config.yaml
Dockerfile
LICENSE
README.rst
catalog-info.yaml
pyproject.toml
.devcontainer/devcontainer.json
.github/CONTRIBUTING.rst
.github/dependabot.yml
.github/actions/install_requirements/action.yml
.github/pages/index.html
.github/pages/make_switcher.py
.github/workflows/code.yml
.github/workflows/docs.yml
.github/workflows/docs_clean.yml
.github/workflows/linkcheck.yml
.vscode/extensions.json
.vscode/launch.json
.vscode/settings.json
.vscode/tasks.json
docs/conf.py
docs/genindex.rst
docs/index.rst
docs/developer/index.rst
docs/developer/explanations/decisions.rst
docs/developer/explanations/decisions/0001-record-architecture-decisions.rst
docs/developer/explanations/decisions/0002-switched-to-pip-skeleton.rst
docs/developer/how-to/build-docs.rst
docs/developer/how-to/contribute.rst
docs/developer/how-to/lint.rst
docs/developer/how-to/make-release.rst
docs/developer/how-to/pin-requirements.rst
docs/developer/how-to/run-tests.rst
docs/developer/how-to/static-analysis.rst
docs/developer/how-to/test-container.rst
docs/developer/how-to/update-tools.rst
docs/developer/reference/standards.rst
docs/developer/tutorials/dev-install.rst
docs/images/dls-favicon.ico
docs/images/dls-logo.svg
docs/user/index.rst
docs/user/explanations/docs-structure.rst
docs/user/how-to/run-container.rst
docs/user/reference/api.rst
docs/user/tutorials/installation.rst
src/i10_bluesky/__init__.py
src/i10_bluesky/__main__.py
src/i10_bluesky/_version.py
src/i10_bluesky.egg-info/PKG-INFO
src/i10_bluesky.egg-info/SOURCES.txt
src/i10_bluesky.egg-info/dependency_links.txt
src/i10_bluesky.egg-info/entry_points.txt
src/i10_bluesky.egg-info/requires.txt
src/i10_bluesky.egg-info/top_level.txt
tests/test_cli.py